gsm_message.cp36-win_amd64.pyd
libgsm_message.a
gsm_message-0.0.9.dist-info/METADATA
gsm_message-0.0.9.dist-info/WHEEL
gsm_message-0.0.9.dist-info/top_level.txt
gsm_message-0.0.9.dist-info/RECORD
