Metadata-Version: 2.1
Name: gsm-message
Version: 0.0.9
Summary: A small package for sending message using gsm
Home-page: UNKNOWN
Author: Zeeshan Iqbal
Author-email: zeeshan.iqbal.cs@gmail.com
License: UNKNOWN
Platform: UNKNOWN
Classifier: Programming Language :: Python :: 3
Classifier: License :: OSI Approved :: MIT License
Classifier: Operating System :: OS Independent
Requires-Python: >=3.6
Requires-Dist: pyserial
Requires-Dist: python-gsmmodem-new
